insult.py
insult-0.6.2.data/scripts/insult
insult-0.6.2.dist-info/licenses/COPYING
insult-0.6.2.dist-info/METADATA
insult-0.6.2.dist-info/WHEEL
insult-0.6.2.dist-info/top_level.txt
insult-0.6.2.dist-info/RECORD
